mlb_odds_scraper/__init__.py
mlb_odds_scraper/scraper.py
mlb_odds_scraper-0.1.20.dist-info/licenses/LICENSE
mlb_odds_scraper-0.1.20.dist-info/METADATA
mlb_odds_scraper-0.1.20.dist-info/WHEEL
mlb_odds_scraper-0.1.20.dist-info/top_level.txt
mlb_odds_scraper-0.1.20.dist-info/RECORD
