Metadata-Version: 2.4
Name: mlb_odds_scraper
Version: 0.1.20
Summary: A package for scraping MLB odds data from OddsPortal
Author-email: Oronto <vile319@gmail.com>
Project-URL: Homepage, https://github.com/Oronto/mlb_odds_scraper
Project-URL: Bug Tracker, https://github.com/Oronto/mlb_odds_scraper/issues
Classifier: Programming Language :: Python :: 3
Classifier: License :: OSI Approved :: MIT License
Classifier: Operating System :: OS Independent
Requires-Python: >=3.8
License-File: LICENSE
Requires-Dist: pandas>=1.0.0
Requires-Dist: selenium>=4.0.0
Requires-Dist: stealthenium>=0.1.0
Requires-Dist: sqlalchemy>=1.4.0
Requires-Dist: MLB-StatsAPI>=1.0.0
Dynamic: license-file
